.condarc
.coveragerc
.gitattributes
.gitignore
.gitmodules
.travis.yml
CMakeLists.txt
INSTALL.md
MANIFEST.in
README.md
__VERSION__
changelog.md
contributors.md
developers.md
distr.sh
install_linux.md
install_nosudo.sh
install_osx.md
install_windows.md
installer.bat
installer.sh
license.txt
lisa.py
lisa.sh
mycoverage.sh
mysetup.py
organ_segmentation.config
requirements.txt
requirements_apt.txt
requirements_conda.txt
requirements_conda_root.txt
requirements_pip.txt
setup.cfg
setup.py
setup_lisa.iss
applications/LISA.ico
applications/LISA256.icns
applications/LISA256.png
applications/ha.bat
applications/ha.desktop.in
applications/ha.sh
applications/lisa.bat
applications/lisa.desktop.in
applications/lisa.sh
applications/lisa_gui
applications/LISA.app/Contents/MacOS/lisa
conda-recipe/bld.bat
conda-recipe/build.sh
conda-recipe/meta.yaml
docs/.gitignore
docs/Makefile
docs/conf.py
docs/index.rst
docs/lisa.extern.rst
docs/lisa.rst
docs/make.bat
docs/pip_requirements.txt
envinstall/CMakeLists.txt.gco.in
envinstall/envubuntu.sh
envinstall/envwindows.bat
envinstall/envwine.sh
examples/datafit.py
examples/read_and_show.ipynb
examples/sitk.py
examples/volumetry_evaluation.ipynb
experiments/20130812_liver_volumetry.yaml
experiments/20130909-array-arrange.py
experiments/20130911_itk.py
experiments/20130919_liver_statistics.yaml
experiments/__init__.py
experiments/exp-spring2014.sh
experiments/experiment_volumetry_evaluation.sh
experiments/experiment_volumetry_run.sh
experiments/features_classifs.py
experiments/liver_volumetry.py
experiments/precise_liver_statistics.py
experiments/sliver_show.py
experiments/tiled_liver_statistics.py
lisa/PavelTestingModule.py
lisa/__init__.py
lisa/__main__.py
lisa/audiosupport.py
lisa/authors.py
lisa/autolisa.py
lisa/body_navigation.py
lisa/classification.py
lisa/config.py
lisa/configEditor.py
lisa/config_default.py
lisa/convert.py
lisa/convert_pkl.py
lisa/data_manipulation.py
lisa/data_plus.py
lisa/dataset.py
lisa/dictEditQt.py
lisa/dictGUI.py
lisa.egg-info/PKG-INFO
lisa.egg-info/SOURCES.txt
lisa.egg-info/dependency_links.txt
lisa.egg-info/pbr.json
lisa.egg-info/top_level.txt
